README.txt
setup.py
tinderpy/__init__.py
tinderpy.egg-info/PKG-INFO
tinderpy.egg-info/SOURCES.txt
tinderpy.egg-info/dependency_links.txt
tinderpy.egg-info/requires.txt
tinderpy.egg-info/top_level.txt