Metadata-Version: 1.0
Name: tinderpy
Version: 0.0.1
Summary: Tinder client for python
Home-page: https://github.com/codenut/tinderpy
Author: Michael Valladolid
Author-email: mikevalladolid@gmail.com
License: MIT
Platform: UNKNOWN
